azure/mgmt/cosmosdbforpostgresql/__init__.py
azure/mgmt/cosmosdbforpostgresql/_configuration.py
azure/mgmt/cosmosdbforpostgresql/_cosmosdb_for_postgresql_mgmt_client.py
azure/mgmt/cosmosdbforpostgresql/_patch.py
azure/mgmt/cosmosdbforpostgresql/_serialization.py
azure/mgmt/cosmosdbforpostgresql/_vendor.py
azure/mgmt/cosmosdbforpostgresql/_version.py
azure/mgmt/cosmosdbforpostgresql/py.typed
azure/mgmt/cosmosdbforpostgresql/aio/__init__.py
azure/mgmt/cosmosdbforpostgresql/aio/_configuration.py
azure/mgmt/cosmosdbforpostgresql/aio/_cosmosdb_for_postgresql_mgmt_client.py
azure/mgmt/cosmosdbforpostgresql/aio/_patch.py
azure/mgmt/cosmosdbforpostgresql/aio/operations/__init__.py
azure/mgmt/cosmosdbforpostgresql/aio/operations/_clusters_operations.py
azure/mgmt/cosmosdbforpostgresql/aio/operations/_configurations_operations.py
azure/mgmt/cosmosdbforpostgresql/aio/operations/_firewall_rules_operations.py
azure/mgmt/cosmosdbforpostgresql/aio/operations/_operations.py
azure/mgmt/cosmosdbforpostgresql/aio/operations/_patch.py
azure/mgmt/cosmosdbforpostgresql/aio/operations/_private_endpoint_connections_operations.py
azure/mgmt/cosmosdbforpostgresql/aio/operations/_private_link_resources_operations.py
azure/mgmt/cosmosdbforpostgresql/aio/operations/_roles_operations.py
azure/mgmt/cosmosdbforpostgresql/aio/operations/_servers_operations.py
azure/mgmt/cosmosdbforpostgresql/models/__init__.py
azure/mgmt/cosmosdbforpostgresql/models/_cosmosdb_for_postgresql_mgmt_client_enums.py
azure/mgmt/cosmosdbforpostgresql/models/_models_py3.py
azure/mgmt/cosmosdbforpostgresql/models/_patch.py
azure/mgmt/cosmosdbforpostgresql/operations/__init__.py
azure/mgmt/cosmosdbforpostgresql/operations/_clusters_operations.py
azure/mgmt/cosmosdbforpostgresql/operations/_configurations_operations.py
azure/mgmt/cosmosdbforpostgresql/operations/_firewall_rules_operations.py
azure/mgmt/cosmosdbforpostgresql/operations/_operations.py
azure/mgmt/cosmosdbforpostgresql/operations/_patch.py
azure_mgmt_cosmosdbforpostgresql-1.0.0.dist-info/LICENSE
azure_mgmt_cosmosdbforpostgresql-1.0.0.dist-info/METADATA
azure_mgmt_cosmosdbforpostgresql-1.0.0.dist-info/WHEEL
azure_mgmt_cosmosdbforpostgresql-1.0.0.dist-info/top_level.txt
azure_mgmt_cosmosdbforpostgresql-1.0.0.dist-info/RECORD
